.coveragerc
.travis.yml
LICENSE
MANIFEST.in
README.rst
setup.cfg
setup.py
Mopidy_EvtDev.egg-info/PKG-INFO
Mopidy_EvtDev.egg-info/SOURCES.txt
Mopidy_EvtDev.egg-info/dependency_links.txt
Mopidy_EvtDev.egg-info/entry_points.txt
Mopidy_EvtDev.egg-info/not-zip-safe
Mopidy_EvtDev.egg-info/requires.txt
Mopidy_EvtDev.egg-info/top_level.txt
mopidy_evtdev/__init__.py
mopidy_evtdev/agent.py
mopidy_evtdev/ext.conf
mopidy_evtdev/frontend.py
tests/__init__.py
tests/test_agent_mocked_uinput.py
tests/test_extension.py