Metadata-Version: 1.1
Name: Mopidy-EvtDev
Version: 0.1.1
Summary: Mopidy extension for virtual input devices
Home-page: https://github.com/liamw9534/mopidy-evtdev
Author: Liam Wickins
Author-email: liamw9534@gmail.com
License: Apache License, Version 2.0
Platform: UNKNOWN
Classifier: Environment :: No Input/Output (Daemon)
Classifier: Intended Audience :: End Users/Desktop
Classifier: License :: OSI Approved :: Apache Software License
Classifier: Operating System :: OS Independent
Classifier: Programming Language :: Python :: 2
Classifier: Topic :: Multimedia :: Sound/Audio :: Players
